[
    {
        "recordTitle": "most goals in history",
        "player": "Cristiano Ronaldo",
        "record": 823
    },
    {
        "recordTitle": "most goals in history",
        "player": "Cristiano Ronaldo",
        "record": 823
    },
    {
        "recordTitle": "most goals in history",
        "player": "Cristiano Ronaldo",
        "record": 823
    },
    {
        "recordTitle": "most goals in history",
        "player": "Cristiano Ronaldo",
        "record": 823
    },
    {
        "recordTitle": "most goals in history",
        "player": "Cristiano Ronaldo",
        "record": 823
    },
    {
        "recordTitle": "most goals in history",
        "player": "Cristiano Ronaldo",
        "record": 823
    },
    {
        "recordTitle": "most goals in history",
        "player": "Cristiano Ronaldo",
        "record": 823
    },
    {
        "recordTitle": "most goals in history",
        "player": "Cristiano Ronaldo",
        "record": 823
    },
    {
        "recordTitle": "most goals in history",
        "player": "Cristiano Ronaldo",
        "record": 823
    }
]
